knnpe/__init__.py
knnpe/knnpe.py
knnpe/rwalk/__init__.py
knnpe/rwalk/config.py
knnpe-0.1.4.dist-info/licenses/LICENSE
knnpe-0.1.4.dist-info/METADATA
knnpe-0.1.4.dist-info/WHEEL
knnpe-0.1.4.dist-info/top_level.txt
knnpe-0.1.4.dist-info/RECORD
