Metadata-Version: 2.4
Name: knnpe
Version: 0.1.4
Summary: A Python package for characterizing unstructured data with the nearest neighbor permutation entropy
Author: L. G. J. M. Voltarelli, A. A. B. Pessa, L. Zunino, R. S. Zola, E. K. Lenzi, M. Perc, H. V. Ribeiro
Author-email: "Haroldo V. Ribeiro" <hvr@dfi.uem.br>
Project-URL: Homepage, https://github.com/hvribeiro/knnpe
Project-URL: Repository, https://github.com/hvribeiro/knnpe
Project-URL: Issues, https://github.com/hvribeiro/knnpe/issues
Classifier: Programming Language :: Python :: 3
Classifier: License :: OSI Approved :: MIT License
Classifier: Operating System :: OS Independent
Requires-Python: >=3.6
License-File: LICENSE
Dynamic: author
Dynamic: license-file
Dynamic: requires-python
